README.md
py3beanstalk.py
setup.py
py3beanstalk.egg-info/PKG-INFO
py3beanstalk.egg-info/SOURCES.txt
py3beanstalk.egg-info/dependency_links.txt
py3beanstalk.egg-info/top_level.txt